mclahe/__init__.py
mclahe/core.py
mclahe/utils.py
mclahe-1.1.0.dist-info/licenses/LICENSE
mclahe-1.1.0.dist-info/METADATA
mclahe-1.1.0.dist-info/WHEEL
mclahe-1.1.0.dist-info/top_level.txt
mclahe-1.1.0.dist-info/RECORD
