Metadata-Version: 2.4
Name: mclahe
Version: 1.1.0
Summary: Tensorflow implementation of the Multidimensional Contrast Limited Adaptive Histogram Equalization (MCLAHE) procedure
Author: Vincent Stimper, R. Patrick Xian
Project-URL: Homepage, https://github.com/mpes-kit/mclahe
Classifier: Development Status :: 3 - Alpha
Classifier: Intended Audience :: Developers
Classifier: Programming Language :: Python :: 3
Requires-Python: >=3.8
License-File: LICENSE
Requires-Dist: numpy<2
Requires-Dist: tensorflow>=2
Provides-Extra: dev
Requires-Dist: ruff>=0.1.7; extra == "dev"
Requires-Dist: mypy>=1.6.0; extra == "dev"
Requires-Dist: pre-commit>=3.0.0; extra == "dev"
Provides-Extra: cuda
Requires-Dist: tensorflow[and-cuda]>=2; extra == "cuda"
Dynamic: license-file
